notsofastapi/__init__.py
notsofastapi/main.py
notsofastapi/request.py
notsofastapi/response.py
notsofastapi2-0.1.0.dist-info/METADATA
notsofastapi2-0.1.0.dist-info/WHEEL
notsofastapi2-0.1.0.dist-info/top_level.txt
notsofastapi2-0.1.0.dist-info/RECORD
